degas/__init__.py
degas/degas.py
degas/styles/default.mplstyle
degas/styles/degas_figure.mplstyle
degas/styles/pastel_rainbow.mplstyle
degas-0.0.0.dist-info/METADATA
degas-0.0.0.dist-info/WHEEL
degas-0.0.0.dist-info/top_level.txt
degas-0.0.0.dist-info/RECORD
