Metadata-Version: 2.1
Name: degas
Version: 0.0.0
Requires-Dist: numpy
Requires-Dist: matplotlib
